LICENSE
MANIFEST.in
README.rst
setup.py
sparnord/__init__.py
sparnord.egg-info/PKG-INFO
sparnord.egg-info/SOURCES.txt
sparnord.egg-info/dependency_links.txt
sparnord.egg-info/requires.txt
sparnord.egg-info/top_level.txt