Metadata-Version: 1.0
Name: sparnord
Version: 0.2
Summary: SparNord home banking screen scraper
Home-page: http://github.com/sorenh/python-sparnord
Author: Soren Hansen
Author-email: soren@linux2go.dk
License: Apache 2.0
Keywords: selenium screenscraping sparnord
Platform: UNKNOWN
